alu.v
/*
 * alu.v
 * Desc: Simple 8-bit ALU
 * Authors: M. S. Peeris <e19275@eng.pdn.ac.lk>,
 *          A. P. T. T. Perera <e19278@eng.pdn.ac.lk>
 * Group: 41
 * Last Modified: 31/05/2023
 */   

/*
// stimulus block
module testbench;
    
    // declare test registers
    reg[7:0] DATA1, DATA2;
    reg[2:0] SELECT;
    wire[7:0] OUTPUT;

    // declare test alu
    alu TESTALU(DATA1, DATA2, SELECT, OUTPUT);

    initial
    begin
        $monitor("DATA1: %d, DATA2: %d, SELECT: %d, OUTPUT: %d, ", 
            DATA1, DATA2, SELECT, OUTPUT);
        $dumpfile("wavedata.vcd");
        $dumpvars(0, testbench);

        SELECT = 3'b000;
        DATA1 = 8'b0000_1000;
        DATA2 = 8'b0110_1000;
        #5 SELECT = 3'b001;
        #5 SELECT = 3'b010;
        #5 SELECT = 3'b011;
        #5 SELECT = 3'b111;
        #5 DATA2 = 8'b0110_1011;
        #5 SELECT = 3'b010;
        #5 DATA1 = 8'b0000_1100;
    end

endmodule
*/

// 8-bit ALU
module alu(
    // declare ports
    input [7:0] DATA1, DATA2,
    input [2:0] SELECT,
    output [7:0] OUTPUT,
    output ZERO  
);
    
    // declare register to store computed value after delay
    reg [7:0] RESULT;

    // implement ALU functionality
    always @ (DATA1, DATA2, SELECT)
    begin
        case (SELECT)
            // 000 - Forward
            3'b000: #1 RESULT = DATA2;
            // 001 - Add
            3'b001: #2 RESULT = DATA1 + DATA2;
            // 010 - And
            3'b010: #1 RESULT = DATA1 & DATA2;
            // 011 - Or
            3'b011: #1 RESULT = DATA1 | DATA2;
            // 1xx - Reserved
            default: RESULT = 8'bxxxx_xxxx;
        endcase
    end   

    // assign computed value to output port
    assign OUTPUT = RESULT;

    // Implement flag for branch if equal (BEQ) functionality
    reg ZERO_REG;

    always @ (RESULT)
    begin
        if (RESULT == 0)
            ZERO_REG = 1;
        else
            ZERO_REG = 0;
    end

    assign ZERO = ZERO_REG;

endmodule

register.v
/*
 * register.v
 * Desc: 8x8 register file
 * Authors: M. S. Peeris <e19275@eng.pdn.ac.lk>,
 *          A. P. T. T. Perera <e19278@eng.pdn.ac.lk>
 * Group: 41
 * Last Modified: 31/05/2023
 */   

/*
// stimulus block
module testbench;

    // adapted from reg_file_tb.v that was provided
    reg [7:0] WRITEDATA;
    reg [2:0] WRITEREG, READREG1, READREG2;
    reg CLK, RESET, WRITEENABLE; 
    wire [7:0] REGOUT1, REGOUT2;
    
    reg_file myregfile(WRITEDATA, REGOUT1, REGOUT2, WRITEREG, READREG1, READREG2, WRITEENABLE, CLK, RESET);
       
    initial
    begin 
        CLK = 1'b1;
        
        // generate files needed to plot the waveform using GTKWave
        $dumpfile("wavedata.vcd");
		$dumpvars(0, testbench);
        
        // assign values with time to input signals to see output 
        RESET = 1'b0;
        WRITEENABLE = 1'b0;
        
        #4
        RESET = 1'b1;
        READREG1 = 3'd0;
        READREG2 = 3'd4;
        
        #6
        RESET = 1'b0;
        
        #2
        WRITEREG = 3'd2;
        WRITEDATA = 8'd95;
        WRITEENABLE = 1'b1;
        
        #7
        WRITEENABLE = 1'b0;
        
        #1
        READREG1 = 3'd2;
        
        #7
        WRITEREG = 3'd1;
        WRITEDATA = 8'd28;
        WRITEENABLE = 1'b1;
        READREG1 = 3'd1;
        
        #8
        WRITEENABLE = 1'b0;
        
        #8
        WRITEREG = 3'd4;
        WRITEDATA = 8'd6;
        WRITEENABLE = 1'b1;
        
        #8
        WRITEDATA = 8'd15;
        WRITEENABLE = 1'b1;
        
        #10
        WRITEENABLE = 1'b0;
        
        #6
        WRITEREG = -3'd1;
        WRITEDATA = 8'd50;
        WRITEENABLE = 1'b1;
        
        #5
        WRITEENABLE = 1'b0;
        
        #10
        $finish;
    end
    
    // clock signal generation
    always
        #4 CLK = ~CLK;
endmodule
*/

// 8x8 register file
module reg_file(
    // declare ports
    input[7:0] IN, // 8 bit data input port
    output[7:0] OUT1, OUT2, // 8 bit data outport ports
    input[2:0] INADDRESS, // 3 bit input address port
    input[2:0] OUT1ADDRESS, OUT2ADDRESS, // 3 bit output address ports
    input WRITE, // write enable signal
    input CLK, // clock signal
    input RESET // register reset signal
);

    // Declare 8x8-bit register file
    reg[7:0] REGISTER[7:0];

    //==========OUTPUT REGISTER HANDLING==========

    // Declare output registers
    reg[7:0] OUT1REGISTER, OUT2REGISTER;

    // asynchronously read output registers
    always @ (OUT1ADDRESS, OUT2ADDRESS, REGISTER[OUT1ADDRESS], REGISTER[OUT2ADDRESS])
    begin
       OUT1REGISTER <= #2 REGISTER[OUT1ADDRESS];
       OUT2REGISTER <= #2 REGISTER[OUT2ADDRESS];
    end

    // Continously write output register values to output ports
    assign OUT1 = OUT1REGISTER;
    assign OUT2 = OUT2REGISTER;


    //==========INPUT REGISTER HANDLING==========

    // synchronously write to input register at positive edge of clock
    // when the WRITE signal is high
    always @ (posedge CLK)
    begin
        if (WRITE == 1'b1) begin
            #1 REGISTER[INADDRESS] = IN;
        end
    end

    //==========REGISTER RESET==========
    // synchronously reset registers at positive edge of clock
    // when the RESET is high
    always @ (posedge CLK)
    begin
        if (RESET == 1'b1) begin
            REGISTER[0] <= #1 8'b000_0000;
            REGISTER[1] <= #1 8'b000_0000;
            REGISTER[2] <= #1 8'b000_0000;
            REGISTER[3] <= #1 8'b000_0000;
            REGISTER[4] <= #1 8'b000_0000;
            REGISTER[5] <= #1 8'b000_0000;
            REGISTER[6] <= #1 8'b000_0000;
            REGISTER[7] <= #1 8'b000_0000;
        end
    end

endmodule

cpu.v
/*
 * cpu.v
 * Desc: CPU implementation with minimal instructions
 * Authors: M. S. Peeris <e19275@eng.pdn.ac.lk>,
 *          A. P. T. T. Perera <e19278@eng.pdn.ac.lk>
 * Group: 41
 * Last Modified: 31/05/2023
 */   

`include "alu.v"
`include "register.v"

module cpu(
    // declare ports
    output[31:0] PC, // 32-bit program counter value
    input[31:0] INSTRUCTION, // 32-bit instruction value
    input CLK,
    input RESET
);

    reg WRITEENABLE; // write enable signal to register file 
    reg MUX_SEL_NEG; // mux select signal to chose between immediate value or register value for alu
    reg MUX_SEL_IMM; // mux select signal to chose between original register or negated value for alu sub instruction
    reg MUX_SEL_JUMP; // mux select signal to add jump address to pc
    reg MUX_SEL_BEQ; // mux select signal to add BEQ jump address to pc
    reg[7:0] ALUIN1, ALUIN2; // alu input registers
    reg[2:0] ALUOP; // alu opcode
    
    // Decode opcode and set control signals
    always @ (INSTRUCTION[31:24])
    begin
        case (INSTRUCTION[31:24])
            // 0 - loadi
            0:  begin
                    ALUOP <= #1 0;
                    MUX_SEL_IMM <= #1 1;
                    MUX_SEL_NEG <= #1 0;
                    WRITEENABLE <= #1 1;
                    MUX_SEL_JUMP <= #1 0;
                    MUX_SEL_BEQ <= #1 0; 
                end
            // 1 - mov
            1:  begin
                    ALUOP <= #1 0;
                    MUX_SEL_IMM <= #1 0;
                    MUX_SEL_NEG <= #1 0;
                    WRITEENABLE <= #1 1;
                    MUX_SEL_JUMP <= #1 0;
                    MUX_SEL_BEQ <= #1 0; 
                end
            // 2 - Add
            2:  begin
                    ALUOP <= #1 1;
                    MUX_SEL_NEG <= #1 0;
                    MUX_SEL_IMM <= #1 0;
                    WRITEENABLE <= #1 1;
                    MUX_SEL_JUMP <= #1 0;
                    MUX_SEL_BEQ <= #1 0;
                end
            // 3 - Sub
            3:  begin
                    ALUOP <= #1 1;
                    MUX_SEL_NEG <= #1 1;
                    MUX_SEL_IMM <= #1 0;
                    WRITEENABLE <= #1 1;
                    MUX_SEL_JUMP <= #1 0;
                    MUX_SEL_BEQ <= #1 0;
                end
            // 4 - And
            4:  begin
                    ALUOP <= #1 2;
                    MUX_SEL_NEG <= #1 0;
                    MUX_SEL_IMM <= #1 0;
                    WRITEENABLE <= #1 1;
                    MUX_SEL_JUMP <= #1 0;
                    MUX_SEL_BEQ <= #1 0;
                end
            // 5 - Or
            5:  begin
                    ALUOP <= #1 3;
                    MUX_SEL_NEG <= #1 0;
                    MUX_SEL_IMM <= #1 0;
                    WRITEENABLE <= #1 1;
                    MUX_SEL_JUMP <= #1 0;
                    MUX_SEL_BEQ <= #1 0;
                end
            // 6 - Jump
            6:  begin
                    MUX_SEL_NEG <= #1 0;
                    MUX_SEL_IMM <= #1 0;
                    WRITEENABLE <= #1 0;
                    MUX_SEL_JUMP <= #1 1;
                    MUX_SEL_BEQ <= #1 0;
                end
            // 7 - BEQ
            7:  begin
                    ALUOP <= #1 1;      // Subtract two operands to compare equality
                    MUX_SEL_NEG <= #1 1;
                    MUX_SEL_IMM <= #1 0;
                    WRITEENABLE <= #1 0;
                    MUX_SEL_JUMP <= #1 0;
                    MUX_SEL_BEQ <= #1 1;
                end
        endcase
    end   

    // initialize register module
    wire[7:0] WRITEDATA, REGOUT1, REGOUT2;
    reg_file cpu_reg_file(
        WRITEDATA, REGOUT1, REGOUT2, 
        INSTRUCTION[18:16], // INSTRUCTION[23:16] 8 bit rd address but uses only last 3 bits for 8x8 register address 
        INSTRUCTION[10:8],  // INSTRUCTION[15:8] 8 bit rt address but uses only last 3 bits for 8x8 register address
        INSTRUCTION[2:0],   // INSTRUCTION[7:0] 8 bit rs address but uses only last 3 bits for 8x8 register address
        WRITEENABLE, CLK, RESET
    );

    // reg to store 2s complement or imm value for the alu input 2
    reg[7:0] TEMP_REG;

    always @ (MUX_SEL_NEG, REGOUT2)
    begin
        if (MUX_SEL_NEG)
            TEMP_REG <= #1 (~REGOUT2) + 1;
        else
            TEMP_REG <= REGOUT2;
    end
    
    always @ (MUX_SEL_IMM, INSTRUCTION[7:0], TEMP_REG)
    begin
        if (MUX_SEL_IMM)
            ALUIN2 <= INSTRUCTION[7:0];
        else
            ALUIN2 <= TEMP_REG;
    end

    always @ (REGOUT1)
        ALUIN1 = REGOUT1;

    
    wire ZERO;

    // initialize alu module
    alu cpu_alu(
        ALUIN1, 
        ALUIN2, 
        ALUOP, 
        WRITEDATA,
        ZERO
    );

    // declare register to hold pc value and calculated next pc value
    reg[31:0] PC_REG, NEXT_PC_REG, SIGN_EXTENDED_TARGET;
    assign PC = PC_REG;

    // update pc at each clock edge
    always @ (posedge CLK)
        #1 PC_REG = NEXT_PC_REG;

    // set pc to reset asynchronously at high reset signal
    always @ (RESET)
    begin
        if (RESET == 1)
        begin
            PC_REG = 0;
            NEXT_PC_REG = 0;
        end
    end

    // increment next pc after pc update
    always @ (PC_REG)
        #1 NEXT_PC_REG = NEXT_PC_REG + 4;

    // Sign extend jump target to 32 bits and convert from a word address to a byte address
    always @ (INSTRUCTION)
        SIGN_EXTENDED_TARGET <= { {24{INSTRUCTION[23]}}, INSTRUCTION[23:16] << 2 };

    // Add jump target to pc
    always @ (MUX_SEL_BEQ, ZERO, MUX_SEL_JUMP)
    begin
        if ((MUX_SEL_BEQ && ZERO) || MUX_SEL_JUMP)
            #2 NEXT_PC_REG = NEXT_PC_REG + SIGN_EXTENDED_TARGET;
    end

endmodule

cpu_tb.v
// Computer Architecture (CO224) - Lab 05
// Design: Testbench of Integrated CPU of Simple Processor
// Author: Isuru Nawinne

`include "cpu.v"

module cpu_tb;

    reg CLK, RESET;
    wire [31:0] PC;
    wire [31:0] INSTRUCTION;
    reg[31:0] INSTRUCTION_REG;
    
    /* 
    ------------------------
     SIMPLE INSTRUCTION MEM
    ------------------------
    */
    
    // TODO: Initialize an array of registers (8x1024) named 'instr_mem' to be used as instruction memory
    reg[7:0] instr_mem[1023:0];
    
    // TODO: Create combinational logic to support CPU instruction fetching, given the Program Counter(PC) value 
    //       (make sure you include the delay for instruction fetching here)   
    always @ (PC)
        #2 INSTRUCTION_REG = {instr_mem[PC + 3], instr_mem[PC + 2], instr_mem[PC + 1], instr_mem[PC]} ;
    assign INSTRUCTION = INSTRUCTION_REG;
 
    initial
    begin
        // Initialize instruction memory with the set of instructions you need execute on CPU
        
        // METHOD 1: manually loading instructions to instr_mem
        //{instr_mem[10'd3], instr_mem[10'd2], instr_mem[10'd1], instr_mem[10'd0]} = 32'b00000000000001000000000000000101;
        //{instr_mem[10'd7], instr_mem[10'd6], instr_mem[10'd5], instr_mem[10'd4]} = 32'b00000000000000100000000000001001;
        //{instr_mem[10'd11], instr_mem[10'd10], instr_mem[10'd9], instr_mem[10'd8]} = 32'b00000010000001100000010000000010;
        
        // METHOD 2: loading instr_mem content from instr_mem.mem file
        $readmemb("programmer/instr_mem.mem", instr_mem);
    end
    
    /* 
    -----
     CPU
    -----
    */
    cpu mycpu(PC, INSTRUCTION, CLK, RESET);

    // counter to iterate through and adress registers in reg_file
    integer i;

    initial
    begin
    
        // generate files needed to plot the waveform using GTKWave
        $dumpfile("cpu_wavedata.vcd");
		$dumpvars(0, cpu_tb);

        for(i = 0; i < 8; i = i +1)
        begin
            $dumpvars(1, cpu_tb.mycpu.cpu_reg_file.REGISTER[i]);
        end
        
        CLK = 1'b0;
        
        // TODO: Reset the CPU (by giving a pulse to RESET signal) to start the program execution
        RESET = 1'b0;
        #4
        RESET = 1'b1;
        #1
        RESET = 1'b0;

        // finish simulation after some time
        #500
        $finish;
        
    end
    
    // clock signal generation
    always
        #4 CLK = ~CLK;
        

endmodule

cpu_wavedata.vcd
$date
	Thu Jun  1 01:06:38 2023
$end
$version
	Icarus Verilog
$end
$timescale
	1s
$end
$scope module cpu_tb $end
$var wire 32 ! PC [31:0] $end
$var wire 32 " INSTRUCTION [31:0] $end
$var reg 1 # CLK $end
$var reg 32 $ INSTRUCTION_REG [31:0] $end
$var reg 1 % RESET $end
$var integer 32 & i [31:0] $end
$scope module mycpu $end
$var wire 1 # CLK $end
$var wire 32 ' INSTRUCTION [31:0] $end
$var wire 32 ( PC [31:0] $end
$var wire 1 % RESET $end
$var wire 1 ) ZERO $end
$var wire 8 * WRITEDATA [7:0] $end
$var wire 8 + REGOUT2 [7:0] $end
$var wire 8 , REGOUT1 [7:0] $end
$var reg 8 - ALUIN1 [7:0] $end
$var reg 8 . ALUIN2 [7:0] $end
$var reg 3 / ALUOP [2:0] $end
$var reg 1 0 MUX_SEL_BEQ $end
$var reg 1 1 MUX_SEL_IMM $end
$var reg 1 2 MUX_SEL_JUMP $end
$var reg 1 3 MUX_SEL_NEG $end
$var reg 32 4 NEXT_PC_REG [31:0] $end
$var reg 32 5 PC_REG [31:0] $end
$var reg 32 6 SIGN_EXTENDED_TARGET [31:0] $end
$var reg 8 7 TEMP_REG [7:0] $end
$var reg 1 8 WRITEENABLE $end
$scope module cpu_alu $end
$var wire 8 9 DATA1 [7:0] $end
$var wire 8 : DATA2 [7:0] $end
$var wire 8 ; OUTPUT [7:0] $end
$var wire 3 < SELECT [2:0] $end
$var wire 1 ) ZERO $end
$var reg 8 = RESULT [7:0] $end
$var reg 1 > ZERO_REG $end
$upscope $end
$scope module cpu_reg_file $end
$var wire 1 # CLK $end
$var wire 8 ? IN [7:0] $end
$var wire 3 @ INADDRESS [2:0] $end
$var wire 8 A OUT1 [7:0] $end
$var wire 3 B OUT1ADDRESS [2:0] $end
$var wire 8 C OUT2 [7:0] $end
$var wire 3 D OUT2ADDRESS [2:0] $end
$var wire 1 % RESET $end
$var wire 1 8 WRITE $end
$var reg 8 E OUT1REGISTER [7:0] $end
$var reg 8 F OUT2REGISTER [7:0] $end
$upscope $end
$upscope $end
$upscope $end
$scope module cpu_tb $end
$scope module mycpu $end
$scope module cpu_reg_file $end
$var reg 8 G \REGISTER[0] [7:0] $end
$upscope $end
$upscope $end
$upscope $end
$scope module cpu_tb $end
$scope module mycpu $end
$scope module cpu_reg_file $end
$var reg 8 H \REGISTER[1] [7:0] $end
$upscope $end
$upscope $end
$upscope $end
$scope module cpu_tb $end
$scope module mycpu $end
$scope module cpu_reg_file $end
$var reg 8 I \REGISTER[2] [7:0] $end
$upscope $end
$upscope $end
$upscope $end
$scope module cpu_tb $end
$scope module mycpu $end
$scope module cpu_reg_file $end
$var reg 8 J \REGISTER[3] [7:0] $end
$upscope $end
$upscope $end
$upscope $end
$scope module cpu_tb $end
$scope module mycpu $end
$scope module cpu_reg_file $end
$var reg 8 K \REGISTER[4] [7:0] $end
$upscope $end
$upscope $end
$upscope $end
$scope module cpu_tb $end
$scope module mycpu $end
$scope module cpu_reg_file $end
$var reg 8 L \REGISTER[5] [7:0] $end
$upscope $end
$upscope $end
$upscope $end
$scope module cpu_tb $end
$scope module mycpu $end
$scope module cpu_reg_file $end
$var reg 8 M \REGISTER[6] [7:0] $end
$upscope $end
$upscope $end
$upscope $end
$scope module cpu_tb $end
$scope module mycpu $end
$scope module cpu_reg_file $end
$var reg 8 N \REGISTER[7] [7:0] $end
$upscope $end
$upscope $end
$upscope $end
$enddefinitions $end
#0
$dumpvars
bx N
bx M
bx L
bx K
bx J
bx I
bx H
bx G
bx F
bx E
bx D
bx C
bx B
bx A
bx @
bx ?
x>
bx =
bx <
bx ;
bx :
bx 9
x8
bx 7
bx 6
bx 5
bx 4
x3
x2
x1
x0
bx /
bx .
bx -
bx ,
bx +
bx *
x)
bx (
bx '
b1000 &
0%
bx $
0#
bx "
bx !
$end
#4
b0 4
b0 !
b0 (
b0 5
1#
1%
#5
b0 N
b0 M
b0 L
b0 K
b0 J
b0 I
b0 H
b0 G
b100 4
0%
#6
b0 6
b0 @
b0 B
b1 D
b1 "
b1 $
b1 '
#7
b1 .
b1 :
00
02
18
03
11
b0 /
b0 <
#8
b0 7
b0 -
b0 9
b0 +
b0 C
b0 F
b0 ,
b0 A
b0 E
0)
0>
b1 *
b1 ;
b1 ?
b1 =
0#
#12
1#
#13
b1 G
b100 !
b100 (
b100 5
#14
b1000 4
#15
b1 -
b1 9
b100 .
b100 :
b100 6
b1 ,
b1 A
b1 E
b1 @
b100 D
b10000000000000100 "
b10000000000000100 $
b10000000000000100 '
#16
b100 *
b100 ;
b100 ?
b100 =
0#
#20
1#
#21
b1000 !
b1000 (
b1000 5
b100 H
#22
b1100 4
#23
b1 .
b1 :
b1000 6
b10 @
b1 D
b111000000100000000000000001 "
b111000000100000000000000001 $
b111000000100000000000000001 '
#24
b0 .
b0 :
10
08
01
13
b1 /
b1 <
b1 *
b1 ;
b1 ?
b1 =
0#
#25
b100 +
b100 C
b100 F
#26
b11111100 .
b11111100 :
b11111100 7
#28
b11111101 *
b11111101 ;
b11111101 ?
b11111101 =
1#
#29
b1100 !
b1100 (
b1100 5
#30
b10000 4
#31
b100 6
b1 @
b1 B
b0 D
b11000000010000000100000000 "
b11000000010000000100000000 $
b11000000010000000100000000 '
#32
00
18
0#
#33
b100 -
b100 9
b1 +
b1 C
b1 F
b100 ,
b100 A
b100 E
#34
b11111111 .
b11111111 :
b11111111 7
#35
b11 *
b11 ;
b11 ?
b11 =
#36
1#
#37
b11 H
b10000 !
b10000 (
b10000 5
#38
b10100 4
#39
b11 -
b11 9
b11111111111111111111111111110100 6
b11 ,
b11 A
b11 E
b101 @
b0 B
b110111111010000000000000000 "
b110111111010000000000000000 $
b110111111010000000000000000 '
#40
b1 .
b1 :
b1 7
12
08
03
0#
#41
b1 -
b1 9
b1 ,
b1 A
b1 E
b100 *
b100 ;
b100 ?
b100 =
#42
b1000 4
#43
b10 *
b10 ;
b10 ?
b10 =
#44
1#
#45
b1000 !
b1000 (
b1000 5
#46
b1100 4
#47
b1000 6
b10 @
b1 D
b111000000100000000000000001 "
b111000000100000000000000001 $
b111000000100000000000000001 '
#48
10
02
13
0#
#49
b11111111 .
b11111111 :
b11111111 7
b11 +
b11 C
b11 F
#50
b11111101 .
b11111101 :
b11111101 7
#51
b11111110 *
b11111110 ;
b11111110 ?
b11111110 =
#52
1#
#53
b1100 !
b1100 (
b1100 5
#54
b10000 4
#55
b100 6
b1 @
b1 B
b0 D
b11000000010000000100000000 "
b11000000010000000100000000 $
b11000000010000000100000000 '
#56
00
18
0#
#57
b11 -
b11 9
b1 +
b1 C
b1 F
b11 ,
b11 A
b11 E
#58
b11111111 .
b11111111 :
b11111111 7
#59
b10 *
b10 ;
b10 ?
b10 =
#60
1#
#61
b10 H
b10000 !
b10000 (
b10000 5
#62
b10100 4
#63
b10 -
b10 9
b11111111111111111111111111110100 6
b10 ,
b10 A
b10 E
b101 @
b0 B
b110111111010000000000000000 "
b110111111010000000000000000 $
b110111111010000000000000000 '
#64
b1 .
b1 :
b1 7
12
08
03
0#
#65
b1 -
b1 9
b1 ,
b1 A
b1 E
b11 *
b11 ;
b11 ?
b11 =
#66
b1000 4
#67
b10 *
b10 ;
b10 ?
b10 =
#68
1#
#69
b1000 !
b1000 (
b1000 5
#70
b1100 4
#71
b1000 6
b10 @
b1 D
b111000000100000000000000001 "
b111000000100000000000000001 $
b111000000100000000000000001 '
#72
10
02
13
0#
#73
b11111111 .
b11111111 :
b11111111 7
b10 +
b10 C
b10 F
#74
b11111110 .
b11111110 :
b11111110 7
#75
b11111111 *
b11111111 ;
b11111111 ?
b11111111 =
#76
1#
#77
b1100 !
b1100 (
b1100 5
#78
b10000 4
#79
b100 6
b1 @
b1 B
b0 D
b11000000010000000100000000 "
b11000000010000000100000000 $
b11000000010000000100000000 '
#80
00
18
0#
#81
b10 -
b10 9
b1 +
b1 C
b1 F
b10 ,
b10 A
b10 E
#82
b11111111 .
b11111111 :
b11111111 7
#83
b1 *
b1 ;
b1 ?
b1 =
#84
1#
#85
b1 H
b10000 !
b10000 (
b10000 5
#86
b10100 4
#87
b1 -
b1 9
b11111111111111111111111111110100 6
b1 ,
b1 A
b1 E
b101 @
b0 B
b110111111010000000000000000 "
b110111111010000000000000000 $
b110111111010000000000000000 '
#88
b1 .
b1 :
b1 7
12
08
03
0#
#89
b10 *
b10 ;
b10 ?
b10 =
#90
b1000 4
#92
1#
#93
b1000 !
b1000 (
b1000 5
#94
b1100 4
#95
b1000 6
b10 @
b1 D
b111000000100000000000000001 "
b111000000100000000000000001 $
b111000000100000000000000001 '
#96
10
02
13
0#
#97
b11111111 .
b11111111 :
b11111111 7
#99
1)
1>
b0 *
b0 ;
b0 ?
b0 =
#100
1#
#101
b10100 !
b10100 (
b10100 5
b10100 4
#102
b11000 4
#103
bx00 6
bx @
bx B
bx D
bx "
bx $
bx '
#104
0#
#105
bx -
bx 9
bx +
bx C
bx F
bx ,
bx A
bx E
#106
bx .
bx :
bx 7
#107
0)
0>
bx *
bx ;
bx ?
bx =
#108
1#
#109
b11000 !
b11000 (
b11000 5
#110
b11100 4
#112
0#
#116
1#
#117
b11100 !
b11100 (
b11100 5
#118
b100000 4
#120
0#
#124
1#
#125
b100000 !
b100000 (
b100000 5
#126
b100100 4
#128
0#
#132
1#
#133
b100100 !
b100100 (
b100100 5
#134
b101000 4
#136
0#
#140
1#
#141
b101000 !
b101000 (
b101000 5
#142
b101100 4
#144
0#
#148
1#
#149
b101100 !
b101100 (
b101100 5
#150
b110000 4
#152
0#
#156
1#
#157
b110000 !
b110000 (
b110000 5
#158
b110100 4
#160
0#
#164
1#
#165
b110100 !
b110100 (
b110100 5
#166
b111000 4
#168
0#
#172
1#
#173
b111000 !
b111000 (
b111000 5
#174
b111100 4
#176
0#
#180
1#
#181
b111100 !
b111100 (
b111100 5
#182
b1000000 4
#184
0#
#188
1#
#189
b1000000 !
b1000000 (
b1000000 5
#190
b1000100 4
#192
0#
#196
1#
#197
b1000100 !
b1000100 (
b1000100 5
#198
b1001000 4
#200
0#
#204
1#
#205
b1001000 !
b1001000 (
b1001000 5
#206
b1001100 4
#208
0#
#212
1#
#213
b1001100 !
b1001100 (
b1001100 5
#214
b1010000 4
#216
0#
#220
1#
#221
b1010000 !
b1010000 (
b1010000 5
#222
b1010100 4
#224
0#
#228
1#
#229
b1010100 !
b1010100 (
b1010100 5
#230
b1011000 4
#232
0#
#236
1#
#237
b1011000 !
b1011000 (
b1011000 5
#238
b1011100 4
#240
0#
#244
1#
#245
b1011100 !
b1011100 (
b1011100 5
#246
b1100000 4
#248
0#
#252
1#
#253
b1100000 !
b1100000 (
b1100000 5
#254
b1100100 4
#256
0#
#260
1#
#261
b1100100 !
b1100100 (
b1100100 5
#262
b1101000 4
#264
0#
#268
1#
#269
b1101000 !
b1101000 (
b1101000 5
#270
b1101100 4
#272
0#
#276
1#
#277
b1101100 !
b1101100 (
b1101100 5
#278
b1110000 4
#280
0#
#284
1#
#285
b1110000 !
b1110000 (
b1110000 5
#286
b1110100 4
#288
0#
#292
1#
#293
b1110100 !
b1110100 (
b1110100 5
#294
b1111000 4
#296
0#
#300
1#
#301
b1111000 !
b1111000 (
b1111000 5
#302
b1111100 4
#304
0#
#308
1#
#309
b1111100 !
b1111100 (
b1111100 5
#310
b10000000 4
#312
0#
#316
1#
#317
b10000000 !
b10000000 (
b10000000 5
#318
b10000100 4
#320
0#
#324
1#
#325
b10000100 !
b10000100 (
b10000100 5
#326
b10001000 4
#328
0#
#332
1#
#333
b10001000 !
b10001000 (
b10001000 5
#334
b10001100 4
#336
0#
#340
1#
#341
b10001100 !
b10001100 (
b10001100 5
#342
b10010000 4
#344
0#
#348
1#
#349
b10010000 !
b10010000 (
b10010000 5
#350
b10010100 4
#352
0#
#356
1#
#357
b10010100 !
b10010100 (
b10010100 5
#358
b10011000 4
#360
0#
#364
1#
#365
b10011000 !
b10011000 (
b10011000 5
#366
b10011100 4
#368
0#
#372
1#
#373
b10011100 !
b10011100 (
b10011100 5
#374
b10100000 4
#376
0#
#380
1#
#381
b10100000 !
b10100000 (
b10100000 5
#382
b10100100 4
#384
0#
#388
1#
#389
b10100100 !
b10100100 (
b10100100 5
#390
b10101000 4
#392
0#
#396
1#
#397
b10101000 !
b10101000 (
b10101000 5
#398
b10101100 4
#400
0#
#404
1#
#405
b10101100 !
b10101100 (
b10101100 5
#406
b10110000 4
#408
0#
#412
1#
#413
b10110000 !
b10110000 (
b10110000 5
#414
b10110100 4
#416
0#
#420
1#
#421
b10110100 !
b10110100 (
b10110100 5
#422
b10111000 4
#424
0#
#428
1#
#429
b10111000 !
b10111000 (
b10111000 5
#430
b10111100 4
#432
0#
#436
1#
#437
b10111100 !
b10111100 (
b10111100 5
#438
b11000000 4
#440
0#
#444
1#
#445
b11000000 !
b11000000 (
b11000000 5
#446
b11000100 4
#448
0#
#452
1#
#453
b11000100 !
b11000100 (
b11000100 5
#454
b11001000 4
#456
0#
#460
1#
#461
b11001000 !
b11001000 (
b11001000 5
#462
b11001100 4
#464
0#
#468
1#
#469
b11001100 !
b11001100 (
b11001100 5
#470
b11010000 4
#472
0#
#476
1#
#477
b11010000 !
b11010000 (
b11010000 5
#478
b11010100 4
#480
0#
#484
1#
#485
b11010100 !
b11010100 (
b11010100 5
#486
b11011000 4
#488
0#
#492
1#
#493
b11011000 !
b11011000 (
b11011000 5
#494
b11011100 4
#496
0#
#500
1#
#501
b11011100 !
b11011100 (
b11011100 5
#502
b11100000 4
